age_mcp_server/__init__.py
age_mcp_server/server.py
age_mcp_server-0.2.38.dist-info/METADATA
age_mcp_server-0.2.38.dist-info/WHEEL
age_mcp_server-0.2.38.dist-info/entry_points.txt
age_mcp_server-0.2.38.dist-info/licenses/LICENSE
age_mcp_server-0.2.38.dist-info/RECORD
