Metadata-Version: 2.4
Name: age-mcp-server
Version: 0.2.38
Summary: Apache AGE MCP Server
Project-URL: Homepage, https://github.com/rioriost/homebrew-age-mcp-server
Project-URL: Issues, https://github.com/rioriost/homebrew-age-mcp-server/issues
Author-email: Rio Fujita <rifujita@microsoft.com>
License: MIT License
License-File: LICENSE
Requires-Python: >=3.13
Requires-Dist: agefreighter>=1.0.27
Requires-Dist: mcp>=1.25.0
Requires-Dist: ply>=3.11
Requires-Dist: psycopg-binary>=3.3.2
Requires-Dist: psycopg-pool>=3.3.0
